odfe_sql_cli/__init__.py
odfe_sql_cli/config.py
odfe_sql_cli/esbuffer.py
odfe_sql_cli/esconnection.py
odfe_sql_cli/esstyle.py
odfe_sql_cli/formatter.py
odfe_sql_cli/main.py
odfe_sql_cli/odfesql_cli.py
odfe_sql_cli/utils.py
odfe_sql_cli/conf/__init__.py
odfe_sql_cli/conf/clirc
odfe_sql_cli/esliterals/__init__.py
odfe_sql_cli/esliterals/esliterals.json
odfe_sql_cli-1.13.0.0.dist-info/LICENSE.TXT
odfe_sql_cli-1.13.0.0.dist-info/METADATA
odfe_sql_cli-1.13.0.0.dist-info/NOTICE
odfe_sql_cli-1.13.0.0.dist-info/WHEEL
odfe_sql_cli-1.13.0.0.dist-info/entry_points.txt
odfe_sql_cli-1.13.0.0.dist-info/top_level.txt
odfe_sql_cli-1.13.0.0.dist-info/RECORD
